LICENSE
README.md
setup.py
starbot/__init__.py
starbot/api/live.json
starbot/api/user.json
starbot/commands/builtin/__init__.py
starbot/commands/builtin/disable_command.py
starbot/commands/builtin/enable_command.py
starbot/commands/builtin/help.py
starbot/commands/builtin/at/dynamic_at_me.py
starbot/commands/builtin/at/dynamic_at_me_cancel.py
starbot/commands/builtin/at/dynamic_at_me_list.py
starbot/commands/builtin/at/live_on_at_me.py
starbot/commands/builtin/at/live_on_at_me_cancel.py
starbot/commands/builtin/at/live_on_at_me_list.py
starbot/commands/builtin/data/bind.py
starbot/commands/builtin/data/report.py
starbot/commands/builtin/data/room_data.py
starbot/commands/builtin/data/room_data_total.py
starbot/commands/builtin/data/user_data.py
starbot/commands/builtin/data/user_data_total.py
starbot/commands/builtin/master/resend.py
starbot/commands/builtin/master/resend_clear_queue.py
starbot/commands/builtin/ranking/ranking.py
starbot/commands/builtin/ranking/ranking_double.py
starbot/core/__init__.py
starbot/core/bot.py
starbot/core/datasource.py
starbot/core/dynamic.py
starbot/core/live.py
starbot/core/model.py
starbot/core/room.py
starbot/core/sender.py
starbot/core/server.py
starbot/core/user.py
starbot/exception/ApiException.py
starbot/exception/AtAllLimitedException.py
starbot/exception/CredentialNoBiliJctException.py
starbot/exception/CredentialNoBuvid3Exception.py
starbot/exception/CredentialNoSessdataException.py
starbot/exception/DataSourceException.py
starbot/exception/LiveException.py
starbot/exception/NetworkException.py
starbot/exception/NoPermissionException.py
starbot/exception/RedisException.py
starbot/exception/ResponseCodeException.py
starbot/exception/ResponseException.py
starbot/exception/__init__.py
starbot/painter/DynamicPicGenerator.py
starbot/painter/LiveReportGenerator.py
starbot/painter/PicGenerator.py
starbot/painter/RankingGenerator.py
starbot/painter/__init__.py
starbot/resource/bold.ttf
starbot/resource/box.png
starbot_bilibili.egg-info/PKG-INFO
starbot_bilibili.egg-info/SOURCES.txt
starbot_bilibili.egg-info/dependency_links.txt
starbot_bilibili.egg-info/requires.txt
starbot_bilibili.egg-info/top_level.txt