Metadata-Version: 2.1
Name: starbot-bilibili
Version: 2.0.18
Summary: 一款极速，多功能的哔哩哔哩推送机器人
Home-page: https://github.com/Starlwr/StarBot
Author: LWR
Author-email: lwr1104@qq.com
License: GNU Affero General Public License v3.0
Keywords: starbot
Platform: UNKNOWN
Requires-Python: >=3.8
License-File: LICENSE
